connectome_manipulator/__init__.py
connectome_manipulator/access_functions.py
connectome_manipulator/cli.py
connectome_manipulator/cli_parallel.py
connectome_manipulator/log.py
connectome_manipulator/processing.py
connectome_manipulator/profiler.py
connectome_manipulator/utils.py
connectome_manipulator/version.py
connectome_manipulator/connectome_comparison/__init__.py
connectome_manipulator/connectome_comparison/adjacency.py
connectome_manipulator/connectome_comparison/connectivity.py
connectome_manipulator/connectome_comparison/properties.py
connectome_manipulator/connectome_comparison/structural_comparator.py
connectome_manipulator/connectome_manipulation/__init__.py
connectome_manipulator/connectome_manipulation/connectome_manipulation.py
connectome_manipulator/connectome_manipulation/converters.py
connectome_manipulator/connectome_manipulation/executors.py
connectome_manipulator/connectome_manipulation/tracker.py
connectome_manipulator/connectome_manipulation/manipulation/__init__.py
connectome_manipulator/connectome_manipulation/manipulation/base.py
connectome_manipulator/connectome_manipulation/manipulation/conn_extraction.py
connectome_manipulator/connectome_manipulation/manipulation/conn_removal.py
connectome_manipulator/connectome_manipulation/manipulation/conn_rewiring.py
connectome_manipulator/connectome_manipulation/manipulation/conn_wiring.py
connectome_manipulator/connectome_manipulation/manipulation/null_manipulation.py
connectome_manipulator/connectome_manipulation/manipulation/syn_prop_alteration.py
connectome_manipulator/connectome_manipulation/manipulation/syn_removal.py
connectome_manipulator/connectome_manipulation/manipulation/syn_subsampling.py
connectome_manipulator/model_building/__init__.py
connectome_manipulator/model_building/conn_prob.py
connectome_manipulator/model_building/conn_prob_adj.py
connectome_manipulator/model_building/conn_props.py
connectome_manipulator/model_building/delay.py
connectome_manipulator-1.0.4.dist-info/licenses/AUTHORS.txt
connectome_manipulator-1.0.4.dist-info/licenses/LICENSE.txt
connectome_manipulator-1.0.4.dist-info/METADATA
connectome_manipulator-1.0.4.dist-info/WHEEL
connectome_manipulator-1.0.4.dist-info/entry_points.txt
connectome_manipulator-1.0.4.dist-info/top_level.txt
connectome_manipulator-1.0.4.dist-info/RECORD
