Metadata-Version: 2.4
Name: connectome-manipulator
Version: 1.0.4
Summary: A connectome manipulation framework for SONATA circuits
Home-page: https://github.com/BlueBrain/connectome-manipulator.git
Author: Blue Brain Project, EPFL
License: Apache-2
Classifier: Development Status :: 4 - Beta
Classifier: Intended Audience :: Education
Classifier: Intended Audience :: Science/Research
Classifier: Programming Language :: Python
Classifier: Programming Language :: Python :: 3
Classifier: Programming Language :: Python :: 3.10
Classifier: Programming Language :: Python :: 3.11
Classifier: Programming Language :: Python :: 3.12
Classifier: Topic :: Scientific/Engineering
Classifier: Topic :: Scientific/Engineering :: Bio-Informatics
Requires-Python: >=3.10
License-File: LICENSE.txt
License-File: AUTHORS.txt
Requires-Dist: bluepysnap>=3.0.1
Requires-Dist: numpy>=1.24.3
Requires-Dist: pandas>=1.5.3
Requires-Dist: progressbar>=2.5
Requires-Dist: pyarrow>=10.0.1
Requires-Dist: scipy>=1.10.1
Requires-Dist: scikit-learn>=1.3.2
Requires-Dist: voxcell>=3.1.5
Requires-Dist: tables>=3.8.0
Requires-Dist: distributed>=2023.4.1
Requires-Dist: dask-mpi>=2022.4.0
Provides-Extra: docs
Requires-Dist: sphinx; extra == "docs"
Requires-Dist: sphinx-bluebrain-theme; extra == "docs"
Dynamic: author
Dynamic: classifier
Dynamic: description
Dynamic: description-content-type
Dynamic: home-page
Dynamic: license
Dynamic: license-file
Dynamic: provides-extra
Dynamic: requires-dist
Dynamic: requires-python
Dynamic: summary
